MANIFEST.in
README.md
requirements.txt
setup.py
bin/concatenate_dict
bin/mogu_minerule
bin/price_option
mogu/__init__.py
mogu/netflow.py
mogu/topology.py
mogu.egg-info/PKG-INFO
mogu.egg-info/SOURCES.txt
mogu.egg-info/dependency_links.txt
mogu.egg-info/not-zip-safe
mogu.egg-info/requires.txt
mogu.egg-info/top_level.txt
mogu/assrule/__init__.py
mogu/assrule/apriori.py
mogu/dynprog/__init__.py
mogu/dynprog/dldist.c
mogu/dynprog/dldist.pyx
mogu/dynprog/lcp.c
mogu/dynprog/lcp.pyx
mogu/econ/__init__.py
mogu/econ/gini.py
mogu/finance/__init__.py
mogu/finance/binomial/BinomialTree.py
mogu/finance/binomial/__init__.py
mogu/finance/binomial/binomialtree.f90
mogu/finance/binomial/binomialtree.pyf
mogu/finance/binomial/f90bintree.py
mogu/fit/__init__.py
mogu/fit/exponential_fit.py
mogu/fit/sigmoid_fit.py
mogu/probxwalk/__init__.py
mogu/probxwalk/xwalk.py
mogu/random/__init__.py
mogu/random/levypath.py
mogu/random/multivariate.py
mogu/spectral/__init__.py
mogu/spectral/dft.py
mogu/spectral/fft.py
mogu/spectral/lanczos_tridiagmat.c
mogu/spectral/lanczos_tridiagmat.pyx
mogu/spectral/lanzcos.py
mogu/tensor/__init__.py
mogu/tensor/decompose.py
mogu/util/__init__.py
mogu/util/deprecation.py
mogu/util/derivatives/__init__.py
mogu/util/derivatives/numerical_gradients.py
mogu/voterank/__init__.py
mogu/voterank/schemes.py
test/socialnetworkranks.csv
test/test_dynprog.py
test/test_finance.py
test/test_fourier.py
test/test_lanzcos.py
test/test_probxwalk.py
test/test_random.py
test/test_simcomplex.py
test/test_socialnetworks.py
test/test_tensordecompose.py