Metadata-Version: 1.1
Name: mogu
Version: 0.8.1
Summary: Collection of Simple Numerical Routines
Home-page: https://github.com/stephenhky/MoguNumerics
Author: Kwan-Yuet Ho
Author-email: stephenhky@yahoo.com.hk
License: MIT
Keywords: mogu numerics computation
Platform: UNKNOWN
Classifier: Topic :: Scientific/Engineering :: Information Analysis
Classifier: Topic :: Scientific/Engineering :: Mathematics
Classifier: Programming Language :: Python :: 3.7
Classifier: Programming Language :: Python :: 3.8
Classifier: Programming Language :: Python :: 3.9
Classifier: Programming Language :: Python :: 3.10
Classifier: Programming Language :: Fortran
Classifier: Programming Language :: Cython
Classifier: Programming Language :: C
Classifier: Topic :: System :: Distributed Computing
Classifier: License :: OSI Approved :: MIT License
